full_adder.v
module full_add(sum,carry,a,b,cin);
input a,b,cin;
output sum,carry;
assign sum=a^b^cin;
assign carry=(a & b) | (cin & (a ^ b));
endmodule

full_adder_verilog_test.v
module full_adder_test_verilog(
	input wire a,
	input wire b,
	input wire cin,
	output wire sum,
	output wire carry
);
full_add full_add(
	.a(a),
	.b(b),
	.cin(cin),
	.sum(sum),
	.carry(carry)
);

initial begin
	$dumpfile("full_add.vcd");
	$dumpvars;
end
endmodule

full_add.vcd
$date
	Sun May 28 23:49:35 2023
$end
$version
	Icarus Verilog
$end
$timescale
	1ps
$end
$scope module full_adder_test_verilog $end
$var wire 1 ! a $end
$var wire 1 " b $end
$var wire 1 # cin $end
$var wire 1 $ sum $end
$var wire 1 % carry $end
$scope module full_add $end
$var wire 1 ! a $end
$var wire 1 " b $end
$var wire 1 % carry $end
$var wire 1 # cin $end
$var wire 1 $ sum $end
$upscope $end
$upscope $end
$enddefinitions $end
#0
$dumpvars
0%
0$
0#
0"
0!
$end
#1000
1$
1#
#2000
0#
1"
#3000
1%
0$
1#
#4000
0%
1$
0#
0"
1!
#5000
1%
0$
1#
#6000
0#
1"
#7000
1$
1#
